odoo/addons/excel_import_export_demo/README.rst
odoo/addons/excel_import_export_demo/__init__.py
odoo/addons/excel_import_export_demo/__manifest__.py
odoo/addons/excel_import_export_demo/i18n/ca.po
odoo/addons/excel_import_export_demo/i18n/excel_import_export_demo.pot
odoo/addons/excel_import_export_demo/i18n/it.po
odoo/addons/excel_import_export_demo/i18n/zh_CN.po
odoo/addons/excel_import_export_demo/import_export_purchase_order/actions.xml
odoo/addons/excel_import_export_demo/import_export_purchase_order/purchase_order.xlsx
odoo/addons/excel_import_export_demo/import_export_purchase_order/templates.xml
odoo/addons/excel_import_export_demo/import_export_sale_order/actions.xml
odoo/addons/excel_import_export_demo/import_export_sale_order/sale_order.xlsx
odoo/addons/excel_import_export_demo/import_export_sale_order/templates.xml
odoo/addons/excel_import_export_demo/import_sale_orders/import_sale_order.xlsx
odoo/addons/excel_import_export_demo/import_sale_orders/menu_action.xml
odoo/addons/excel_import_export_demo/import_sale_orders/templates.xml
odoo/addons/excel_import_export_demo/readme/CONTRIBUTORS.rst
odoo/addons/excel_import_export_demo/readme/DESCRIPTION.rst
odoo/addons/excel_import_export_demo/readme/INSTALL.rst
odoo/addons/excel_import_export_demo/readme/USAGE.rst
odoo/addons/excel_import_export_demo/report_action/__init__.py
odoo/addons/excel_import_export_demo/report_action/partner_list/__init__.py
odoo/addons/excel_import_export_demo/report_action/partner_list/partner_list.xlsx
odoo/addons/excel_import_export_demo/report_action/partner_list/report.xml
odoo/addons/excel_import_export_demo/report_action/partner_list/report_partner_list.py
odoo/addons/excel_import_export_demo/report_action/partner_list/report_partner_list.xml
odoo/addons/excel_import_export_demo/report_action/partner_list/templates.xml
odoo/addons/excel_import_export_demo/report_action/partner_list/security/ir.model.access.csv
odoo14_addon_excel_import_export_demo-14.0.1.0.1.dev10.dist-info/METADATA
odoo14_addon_excel_import_export_demo-14.0.1.0.1.dev10.dist-info/WHEEL
odoo14_addon_excel_import_export_demo-14.0.1.0.1.dev10.dist-info/top_level.txt
odoo14_addon_excel_import_export_demo-14.0.1.0.1.dev10.dist-info/RECORD
